LICENSE
README.md
setup.py
utilint/__init__.py
utilint/_times.py
utilint/_utils.py
utilint/locations.py
utilint.egg-info/PKG-INFO
utilint.egg-info/SOURCES.txt
utilint.egg-info/dependency_links.txt
utilint.egg-info/requires.txt
utilint.egg-info/top_level.txt